{
  "schemaVersion": 1,
  "id": "starcrestaddons",
  "version": "1.0.0",
  "name": "Starcrest Addons",
  "description": "Adds base64 link decoding and image viewing features for Hypixel bridge bots",
  "authors": [
    "Stiwyy"
  ],
  "contact": {
    "homepage": "https://github.com/Stiwyy/starcrestaddons_fabric",
    "sources": "https://github.com/Stiwyy/starcrestaddons_fabric"
  },
  "license": "MIT",
  "icon": "assets/starcrestaddons/icon.png",
  "environment": "client",
  "entrypoints": {
    "main": [
      "me.stiwy.starcrestaddons.Starcrestaddons"
    ],
    "client": [
      "me.stiwy.starcrestaddons.client.StarcrestaddonsClient"
    ]
  },
  "mixins": [
    "starcrestaddons.mixins.json"
  ],
  "depends": {
    "fabricloader": ">=0.16.9",
    "minecraft": "~1.21.5",
    "java": ">=21",
    "fabric-api": "*"
  },
  "suggests": {
    "another-mod": "*"
  }
}